java_code_chunker/__init__.py
java_code_chunker/chunker.py
java_code_chunker-0.2.0.dist-info/METADATA
java_code_chunker-0.2.0.dist-info/WHEEL
java_code_chunker-0.2.0.dist-info/licenses/LICENSE
java_code_chunker-0.2.0.dist-info/RECORD
