Metadata-Version: 2.1
Name: java-code-chunker
Version: 0.2.0
Summary: Chunks Java type and member code extracts into a list made up of indexable dictionaries.
Project-URL: Homepage, https://github.com/break-free/java-code-chunker
Project-URL: Issues, https://github.com/break-free/java-code-chunker/issues
Author-email: Chris Mills <cmills@breakfreesolutions.com>
License-File: LICENSE
Classifier: License :: OSI Approved :: MIT License
Classifier: Operating System :: OS Independent
Classifier: Programming Language :: Python :: 3
Requires-Python: >=3.7
Requires-Dist: javalang
